sg_antinuke-0.1.0.dist-info/WHEEL
sg_antinuke-0.1.0.dist-info/top_level.txt
sg_antinuke-0.1.0.dist-info/METADATA
sg_antinuke-0.1.0.dist-info/RECORD
sg_antinuke/redis_support.cpython-312-x86_64-linux-gnu.so
sg_antinuke/redis_support.c
sg_antinuke/antinuke.cpython-312-x86_64-linux-gnu.so
sg_antinuke/antinuke.c
sg_antinuke/__init__.py
