Metadata-Version: 2.4
Name: sg-antinuke
Version: 0.1.0
Summary: Reusable Anti-Nuke Discord cog from SassGuard
Author-email: techcodes27 <sassguard@sassguard.app>
License: Proprietary
Classifier: Programming Language :: Python :: 3
Classifier: License :: Other/Proprietary License
Classifier: Operating System :: OS Independent
Requires-Python: >=3.10
Requires-Dist: discord.py>=2.3
Requires-Dist: aiohttp
Requires-Dist: aiofiles
Provides-Extra: redis
Requires-Dist: redis>=5.0; extra == "redis"
